pytemporal-1.4.27.dist-info/METADATA
pytemporal-1.4.27.dist-info/WHEEL
pytemporal-1.4.27.dist-info/licenses/LICENSE-APACHE
pytemporal-1.4.27.dist-info/licenses/LICENSE-MIT
pytemporal/__init__.py
pytemporal/processor.py
pytemporal/pytemporal.cpython-312-darwin.so
pytemporal-1.4.27.dist-info/RECORD
