Metadata-Version: 2.4
Name: pytemporal
Version: 1.4.27
Classifier: Development Status :: 4 - Beta
Classifier: Intended Audience :: Developers
Classifier: Intended Audience :: Financial and Insurance Industry
Classifier: Intended Audience :: Science/Research
Classifier: License :: OSI Approved :: MIT License
Classifier: License :: OSI Approved :: Apache Software License
Classifier: Operating System :: OS Independent
Classifier: Programming Language :: Python :: 3
Classifier: Programming Language :: Python :: 3.9
Classifier: Programming Language :: Python :: 3.10
Classifier: Programming Language :: Python :: 3.11
Classifier: Programming Language :: Python :: 3.12
Classifier: Programming Language :: Rust
Classifier: Topic :: Database
Classifier: Topic :: Scientific/Engineering
Classifier: Topic :: Software Development :: Libraries :: Python Modules
Requires-Dist: pyarrow>=14.0.0
Requires-Dist: pandas>=2.0.0
Requires-Dist: numpy>=1.24.0
Requires-Dist: arro3-core
Requires-Dist: psutil>=7.0.0
Requires-Dist: pytest>=7.0 ; extra == 'dev'
Requires-Dist: pytest-benchmark ; extra == 'dev'
Requires-Dist: black ; extra == 'dev'
Requires-Dist: mypy ; extra == 'dev'
Requires-Dist: ruff ; extra == 'dev'
Provides-Extra: dev
License-File: LICENSE-APACHE
License-File: LICENSE-MIT
Summary: High-performance bitemporal data processing for Python
Keywords: bitemporal,timeseries,data-processing,temporal,analytics
Home-Page: https://github.com/gingermike/pytemporal
Author: PyTemporal Contributors
License: MIT OR Apache-2.0
Requires-Python: >=3.9
Project-URL: Homepage, https://github.com/gingermike/pytemporal
Project-URL: Repository, https://github.com/gingermike/pytemporal
Project-URL: Documentation, https://gingermike.github.io/pytemporal/
Project-URL: Changelog, https://github.com/gingermike/pytemporal/blob/main/CHANGELOG.md
Project-URL: Issue Tracker, https://github.com/gingermike/pytemporal/issues
Project-URL: Performance Benchmarks, https://gingermike.github.io/pytemporal/
